Metadata-Version: 2.1
Name: dp-tap-postgres
Version: 0.2.50
Summary: Singer.io tap for extracting data from PostgreSQL
Home-page: https://singer.io
Author: Stitch
License: UNKNOWN
Platform: UNKNOWN
Classifier: Programming Language :: Python :: 3 :: Only
Provides-Extra: dev
License-File: LICENSE
